soc_python/__init__.py
soc_python/__main__.py
soc_python/cli.py
soc_python/client.py
soc_python/executor.py
soc_python/t.py
soc_python-0.1.1.dist-info/METADATA
soc_python-0.1.1.dist-info/WHEEL
soc_python-0.1.1.dist-info/entry_points.txt
soc_python-0.1.1.dist-info/top_level.txt
soc_python-0.1.1.dist-info/RECORD
