Metadata-Version: 2.4
Name: soc-python
Version: 0.1.1
Summary: SOC工具执行器 - 执行本地Python文件并通过HTTP API提交
Author-email: liuzhuo <liuzhuo@example.com>
License: MIT
Project-URL: Homepage, https://github.com/liuzhuogood/soc-python
Project-URL: Repository, https://github.com/liuzhuogood/soc-python.git
Project-URL: Issues, https://github.com/liuzhuogood/soc-python/issues
Keywords: soc,security,automation,http-client
Classifier: Development Status :: 4 - Beta
Classifier: Intended Audience :: Developers
Classifier: Intended Audience :: System Administrators
Classifier: License :: OSI Approved :: MIT License
Classifier: Operating System :: OS Independent
Classifier: Programming Language :: Python :: 3
Classifier: Programming Language :: Python :: 3.7
Classifier: Programming Language :: Python :: 3.8
Classifier: Programming Language :: Python :: 3.9
Classifier: Programming Language :: Python :: 3.10
Classifier: Programming Language :: Python :: 3.11
Classifier: Topic :: Internet :: WWW/HTTP :: HTTP Servers
Classifier: Topic :: Security
Classifier: Topic :: System :: Systems Administration
Requires-Python: >=3.7
Requires-Dist: requests>=2.25.0
Provides-Extra: dev
Requires-Dist: pytest>=6.0; extra == "dev"
Requires-Dist: pytest-cov; extra == "dev"
Requires-Dist: black; extra == "dev"
Requires-Dist: flake8; extra == "dev"
Requires-Dist: mypy; extra == "dev"
